setup.py
docsfromtests/__init__.py
docsfromtests/collector.py
docsfromtests/conf.py
docsfromtests/testcase.py
drf_docs_from_tests.egg-info/PKG-INFO
drf_docs_from_tests.egg-info/SOURCES.txt
drf_docs_from_tests.egg-info/dependency_links.txt
drf_docs_from_tests.egg-info/requires.txt
drf_docs_from_tests.egg-info/top_level.txt