Metadata-Version: 1.1
Name: drf-docs-from-tests
Version: 0.1.0
Summary: Stuff for generating docs from api-tests (djangorestframework).
Home-page: https://github.com/scailer/drf-docs-from-tests/
Author: Dmitriy Vlasov
Author-email: scailer@yandex.ru
License: MIT license
Platform: UNKNOWN
Classifier: Framework :: Django
Classifier: Development Status :: 4 - Beta
Classifier: Environment :: Web Environment
Classifier: Intended Audience :: Developers
Classifier: License :: OSI Approved :: MIT License
Classifier: Programming Language :: Python
Classifier: Programming Language :: Python :: 2
Classifier: Programming Language :: Python :: 2.6
Classifier: Programming Language :: Python :: 2.7
Classifier: Topic :: Software Development :: Libraries :: Python Modules
